msiutils/__init__.py
msiutils/__main__.py
msiutils/dump.py
msiutils/extract.py
msiutils/msicore.py
msiutils/msidiff.py
msiutils/msiinfo.py
msiutils/msiutils.py
msiutils/data/msibuild
msiutils/data/msidiff
msiutils/data/msidump
msiutils/data/msiextract
msiutils/data/msiinfo
msi_utils-0.0.4.dist-info/LICENSE.md
msi_utils-0.0.4.dist-info/METADATA
msi_utils-0.0.4.dist-info/WHEEL
msi_utils-0.0.4.dist-info/entry_points.txt
msi_utils-0.0.4.dist-info/top_level.txt
msi_utils-0.0.4.dist-info/RECORD
