Metadata-Version: 2.1
Name: msi-utils
Version: 0.0.4
Summary: A Python package to assist with analzying and extracting data from a Windows Installer MSI
Home-page: https://github.com/MSAdministrator/msiutils
Author: MSAdministrator
Author-email: rickardja@live.com
License: MIT
Keywords: carcass
Platform: UNKNOWN
Requires-Python: >=3.6, <4
Requires-Dist: fire
